{
	"id":"EdnaCatch", "name":"Edna Catch player","type":"cutscene","AppliesTo":"Edna",

	"condition":[
	],
	
	"startup" : [
		{ "type":"SetFlag", "rep":true, "del":0, "id1":"EdnaBrowsingFridge", "id2":"", "sv":"", "iv":0, "dv":"", "vv":[] },
		{ "type":"Speak", "id1":"Edna", "sv":"Gotcha!", "dv":"F" },
		{ "type":"Fade", "rep":true, "del":0.5, "iv":"0" },
		{ "type":"ShowRoom", "rep":true, "del":0, "sv":"Dungeon", "vv":[-93, 10] },
		{ "type":"Teleport", "rep":true, "del":0, "id1":"Edna", "id2":"", "sv":"Dungeon", "iv":"", "dv":"B", "vv":[-91,6.9] },
		{ "type":"Teleport", "rep":true, "del":0, "id1":"current", "id2":"", "sv":"Dungeon", "iv":"", "dv":"B", "vv":[-93,6.9] },
		{ "type":"Fade", "rep":true, "del":0.5, "iv":"1" },
		{ "type":"Expression", "id1":"Current", "sv":"Sad", "dv":"R", "del":.01 },
		{ "type":"Expression", "id1":"Edna", "sv":"Normal", "dv":"L", "del":.01 }
	],
	
	"shutdown" : [
		{ "type":"WalkToPos", "id1":"Edna", "vv":[-87.55,7.58], "dv":"B" },
		{ "type":"Teleport", "rep":true, "del":0, "id1":"Edna", "id2":"", "sv":"Kitchen", "iv":"", "dv":"B", "vv":[-80.12,17.9] },
		{ "type":"Open", "id1":"DungeonDoor", "sv":"c" },
		{ "type":"Open", "id1":"DungeonDoor", "sv":"l" }
	],
	
	"sequence":[
		{ "name":"Message Dave",
			"condition":[{ "type":"CurrentActorIs", "id":"Dave", "bv":true }],
			"action":[{ "type":"Speak", "id1":"Edna", "sv":"Oh dear,\nnext time I will tie you to my bed!\n\nBack to my business!", "dv":"L" },{ "type":"CompleteStep", "del":.2 }]
		},
		{ "name":"Message Bernard",
			"condition":[{ "type":"CurrentActorIs", "id":"Bernard", "bv":true }],
			"action":[{ "type":"Speak", "id1":"Edna", "sv":"Here your brain will have time to rot.\nYou can only think about\nall the mangas you read.\n\nHappy dying!", "dv":"L" },{ "type":"CompleteStep", "del":.2 }]
		},
		{ "name":"Message Wendy",
			"condition":[{ "type":"CurrentActorIs", "id":"Wendy", "bv":true }],
			"action":[{ "type":"Speak", "id1":"Edna", "sv":"You don't know that girls\nshould not be curious?\nHave some time here to think about it.", "dv":"L" },{ "type":"CompleteStep", "del":.2 }]
		},
		{ "name":"Message Syd",
			"condition":[{ "type":"CurrentActorIs", "id":"Syd", "bv":true }],
			"action":[{ "type":"Speak", "id1":"Edna", "sv":"Oh dear,\nI should have brought you to\nmy room and tied you to my bed!\n\nHow silly I am!", "dv":"L" },{ "type":"CompleteStep", "del":.2 }]
		},
		{ "name":"Message Javid",
			"condition":[{ "type":"CurrentActorIs", "id":"Javid", "bv":true }],
			"action":[{ "type":"Speak", "id1":"Edna", "sv":"You can try to develop an escape plan.\nMaybe a OLC-PGE-Escape.\nOr build a robot to save you.\n\nHappy dying!", "dv":"L" },{ "type":"CompleteStep", "del":.2 }]
		},
		{ "name":"Message Ollie",
			"condition":[{ "type":"CurrentActorIs", "id":"Ollie", "bv":true }],
			"action":[{ "type":"Speak", "id1":"Edna", "sv":"Here you will have time\nto play some music.\nSadly there are no waves\nto go surfing.\n\nAnd, please, no more Castelvania!", "dv":"L" },{ "type":"CompleteStep", "del":.2 }]
		}
		
	]

}




